{
	"items": [
		{ "id": 32089, "enchant": 3002, "gems": [30551, 34220] },
		{ "id": 28134 },
		{ "id": 35343, "enchant": 2982, "gems": [30586, 24030] },
		{ "id": 25777, "enchant": 2621 },
		{ "id": 21848, "enchant": 2661, "gems": [28123, 24030] },
		{ "id": 28411, "enchant": 2650, "gems": [30588] },
		{ "id": 21847, "enchant": 2937, "gems": [24030, 28118] },
		{ "id": 21846, "gems": [24030, 30600] },
		{ "id": 24262, "enchant": 2748, "gems": [24030, 24030, 24030] },
		{ "id": 28410, "enchant": 2940 },
		{ "id": 28227 },
		{ "id": 29172 },
		{ "id": 29370 },
		{ "id": 27683 },
		{ "id": 29155, "enchant": 2671 },
		{ "id": 29271 },
		{ "id": 29350 }
	]
}
